[
  {
    "id": "pgmx7te",
    "title": "AMZN news catalyst could spark rally",
    "author": "user_3889",
    "subreddit": "wallstreetbets",
    "score": 2386,
    "num_comments": 92,
    "created_utc": 1759073733.1687126,
    "url": "https://reddit.com/r/wallstreetbets/",
    "timestamp": "2025-09-28T21:16:41.168852+00:00",
    "selftext": "Demo analysis for AMZN. This is fallback data - click to visit r/wallstreetbets.",
    "upvote_ratio": 0.856761859487337,
    "over_18": false,
    "stickied": false,
    "comments": 295
  },
  {
    "id": "7ij50jm",
    "title": "Hold or sell GME? Need advice",
    "author": "user_6555",
    "subreddit": "stocks",
    "score": 2346,
    "num_comments": 284,
    "created_utc": 1759060986.1687126,
    "url": "https://reddit.com/r/stocks/",
    "timestamp": "2025-09-28T21:16:41.169062+00:00",
    "selftext": "Demo analysis for GME. This is fallback data - click to visit r/stocks.",
    "upvote_ratio": 0.8552852248496375,
    "over_18": false,
    "stickied": false,
    "comments": 27
  },
  {
    "id": "vd3gs9f",
    "title": "META earnings beat expectations - bullish outlook",
    "author": "user_5942",
    "subreddit": "wallstreetbets",
    "score": 2247,
    "num_comments": 212,
    "created_utc": 1759093312.1687126,
    "url": "https://reddit.com/r/wallstreetbets/",
    "timestamp": "2025-09-28T21:16:41.168920+00:00",
    "selftext": "Demo analysis for META. This is fallback data - click to visit r/wallstreetbets.",
    "upvote_ratio": 0.765771462095274,
    "over_18": false,
    "stickied": false,
    "comments": 178
  },
  {
    "id": "gl45xih",
    "title": "Why GME is the play of the decade",
    "author": "user_1405",
    "subreddit": "investing",
    "score": 2156,
    "num_comments": 157,
    "created_utc": 1759087276.1687126,
    "url": "https://reddit.com/r/investing/",
    "timestamp": "2025-09-28T21:16:41.169041+00:00",
    "selftext": "Demo analysis for GME. This is fallback data - click to visit r/investing.",
    "upvote_ratio": 0.9490936203318014,
    "over_18": false,
    "stickied": false,
    "comments": 51
  },
  {
    "id": "m9jyprx",
    "title": "\ud83d\ude80 TSLA to the moon! DD inside",
    "author": "user_3929",
    "subreddit": "wallstreetbets",
    "score": 2058,
    "num_comments": 290,
    "created_utc": 1759069762.1687126,
    "url": "https://reddit.com/r/wallstreetbets/",
    "timestamp": "2025-09-28T21:16:41.168864+00:00",
    "selftext": "Demo analysis for TSLA. This is fallback data - click to visit r/wallstreetbets.",
    "upvote_ratio": 0.7133291002638539,
    "over_18": false,
    "stickied": false,
    "comments": 125
  },
  {
    "id": "wo7y5bg",
    "title": "TSLA news catalyst could spark rally",
    "author": "user_8647",
    "subreddit": "wallstreetbets",
    "score": 2049,
    "num_comments": 265,
    "created_utc": 1759053522.1687126,
    "url": "https://reddit.com/r/wallstreetbets/",
    "timestamp": "2025-09-28T21:16:41.168750+00:00",
    "selftext": "Demo analysis for TSLA. This is fallback data - click to visit r/wallstreetbets.",
    "upvote_ratio": 0.8887858435058623,
    "over_18": false,
    "stickied": false,
    "comments": 61
  },
  {
    "id": "nudmxk1",
    "title": "My SPY position is printing \ud83d\udcb0",
    "author": "user_4850",
    "subreddit": "wallstreetbets",
    "score": 1863,
    "num_comments": 204,
    "created_utc": 1759071150.1687126,
    "url": "https://reddit.com/r/wallstreetbets/",
    "timestamp": "2025-09-28T21:16:41.168888+00:00",
    "selftext": "Demo analysis for SPY. This is fallback data - click to visit r/wallstreetbets.",
    "upvote_ratio": 0.8406040110407873,
    "over_18": false,
    "stickied": false,
    "comments": 67
  },
  {
    "id": "anav2l9",
    "title": "My AMZN position is printing \ud83d\udcb0",
    "author": "user_3214",
    "subreddit": "wallstreetbets",
    "score": 1857,
    "num_comments": 99,
    "created_utc": 1759075531.1687126,
    "url": "https://reddit.com/r/wallstreetbets/",
    "timestamp": "2025-09-28T21:16:41.168841+00:00",
    "selftext": "Demo analysis for AMZN. This is fallback data - click to visit r/wallstreetbets.",
    "upvote_ratio": 0.7682790184468111,
    "over_18": false,
    "stickied": false,
    "comments": 197
  },
  {
    "id": "v2y0yao",
    "title": "SPY short squeeze potential?",
    "author": "user_5228",
    "subreddit": "investing",
    "score": 1714,
    "num_comments": 251,
    "created_utc": 1759081225.1687126,
    "url": "https://reddit.com/r/investing/",
    "timestamp": "2025-09-28T21:16:41.168786+00:00",
    "selftext": "Demo analysis for SPY. This is fallback data - click to visit r/investing.",
    "upvote_ratio": 0.9202483045945309,
    "over_18": false,
    "stickied": false,
    "comments": 289
  },
  {
    "id": "5xdf0ia",
    "title": "NVDA dip - perfect entry point?",
    "author": "user_5034",
    "subreddit": "wallstreetbets",
    "score": 1670,
    "num_comments": 103,
    "created_utc": 1759081347.1687126,
    "url": "https://reddit.com/r/wallstreetbets/",
    "timestamp": "2025-09-28T21:16:41.169083+00:00",
    "selftext": "Demo analysis for NVDA. This is fallback data - click to visit r/wallstreetbets.",
    "upvote_ratio": 0.8046390783507805,
    "over_18": false,
    "stickied": false,
    "comments": 273
  },
  {
    "id": "e8w68k3",
    "title": "Technical analysis: NVDA breakout incoming",
    "author": "user_3427",
    "subreddit": "wallstreetbets",
    "score": 1525,
    "num_comments": 128,
    "created_utc": 1759087011.1687126,
    "url": "https://reddit.com/r/wallstreetbets/",
    "timestamp": "2025-09-28T21:16:41.168808+00:00",
    "selftext": "Demo analysis for NVDA. This is fallback data - click to visit r/wallstreetbets.",
    "upvote_ratio": 0.8249817892509557,
    "over_18": false,
    "stickied": false,
    "comments": 49
  },
  {
    "id": "ch3dowg",
    "title": "Bought 1000 shares of MSFT - YOLO",
    "author": "user_5624",
    "subreddit": "stocks",
    "score": 1431,
    "num_comments": 208,
    "created_utc": 1759063931.1687126,
    "url": "https://reddit.com/r/stocks/",
    "timestamp": "2025-09-28T21:16:41.168995+00:00",
    "selftext": "Demo analysis for MSFT. This is fallback data - click to visit r/stocks.",
    "upvote_ratio": 0.8059181785941562,
    "over_18": false,
    "stickied": false,
    "comments": 265
  },
  {
    "id": "57miyeb",
    "title": "\ud83d\ude80 AAPL to the moon! DD inside",
    "author": "user_1177",
    "subreddit": "investing",
    "score": 1367,
    "num_comments": 99,
    "created_utc": 1759066556.1687126,
    "url": "https://reddit.com/r/investing/",
    "timestamp": "2025-09-28T21:16:41.168984+00:00",
    "selftext": "Demo analysis for AAPL. This is fallback data - click to visit r/investing.",
    "upvote_ratio": 0.8539084879363906,
    "over_18": false,
    "stickied": false,
    "comments": 229
  },
  {
    "id": "lc2bhtc",
    "title": "GOOGL earnings beat expectations - bullish outlook",
    "author": "user_9825",
    "subreddit": "wallstreetbets",
    "score": 1259,
    "num_comments": 247,
    "created_utc": 1759068643.1687126,
    "url": "https://reddit.com/r/wallstreetbets/",
    "timestamp": "2025-09-28T21:16:41.169051+00:00",
    "selftext": "Demo analysis for GOOGL. This is fallback data - click to visit r/wallstreetbets.",
    "upvote_ratio": 0.7290452171332692,
    "over_18": false,
    "stickied": false,
    "comments": 270
  },
  {
    "id": "32druoo",
    "title": "NVDA short squeeze potential?",
    "author": "user_8128",
    "subreddit": "stocks",
    "score": 1235,
    "num_comments": 133,
    "created_utc": 1759061637.1687126,
    "url": "https://reddit.com/r/stocks/",
    "timestamp": "2025-09-28T21:16:41.169017+00:00",
    "selftext": "Demo analysis for NVDA. This is fallback data - click to visit r/stocks.",
    "upvote_ratio": 0.8750294442238395,
    "over_18": false,
    "stickied": false,
    "comments": 183
  },
  {
    "id": "he4lcst",
    "title": "GME news catalyst could spark rally",
    "author": "user_7461",
    "subreddit": "stocks",
    "score": 1087,
    "num_comments": 126,
    "created_utc": 1759068050.1687126,
    "url": "https://reddit.com/r/stocks/",
    "timestamp": "2025-09-28T21:16:41.169006+00:00",
    "selftext": "Demo analysis for GME. This is fallback data - click to visit r/stocks.",
    "upvote_ratio": 0.8338488332450262,
    "over_18": false,
    "stickied": false,
    "comments": 55
  },
  {
    "id": "s2x5a2g",
    "title": "TSLA dip - perfect entry point?",
    "author": "user_7388",
    "subreddit": "investing",
    "score": 1029,
    "num_comments": 173,
    "created_utc": 1759080246.1687126,
    "url": "https://reddit.com/r/investing/",
    "timestamp": "2025-09-28T21:16:41.168942+00:00",
    "selftext": "Demo analysis for TSLA. This is fallback data - click to visit r/investing.",
    "upvote_ratio": 0.7223294674415257,
    "over_18": false,
    "stickied": false,
    "comments": 227
  },
  {
    "id": "5txvvm2",
    "title": "GME dip - perfect entry point?",
    "author": "user_9460",
    "subreddit": "wallstreetbets",
    "score": 1019,
    "num_comments": 167,
    "created_utc": 1759088177.1687126,
    "url": "https://reddit.com/r/wallstreetbets/",
    "timestamp": "2025-09-28T21:16:41.168898+00:00",
    "selftext": "Demo analysis for GME. This is fallback data - click to visit r/wallstreetbets.",
    "upvote_ratio": 0.7114638892173913,
    "over_18": false,
    "stickied": false,
    "comments": 159
  },
  {
    "id": "70ct2qw",
    "title": "Bought 1000 shares of MSFT - YOLO",
    "author": "user_7796",
    "subreddit": "investing",
    "score": 969,
    "num_comments": 25,
    "created_utc": 1759086675.1687126,
    "url": "https://reddit.com/r/investing/",
    "timestamp": "2025-09-28T21:16:41.169030+00:00",
    "selftext": "Demo analysis for MSFT. This is fallback data - click to visit r/investing.",
    "upvote_ratio": 0.7797188504418524,
    "over_18": false,
    "stickied": false,
    "comments": 219
  },
  {
    "id": "kfzrxp7",
    "title": "Why AMZN is the play of the decade",
    "author": "user_4721",
    "subreddit": "stocks",
    "score": 961,
    "num_comments": 244,
    "created_utc": 1759080874.1687126,
    "url": "https://reddit.com/r/stocks/",
    "timestamp": "2025-09-28T21:16:41.168971+00:00",
    "selftext": "Demo analysis for AMZN. This is fallback data - click to visit r/stocks.",
    "upvote_ratio": 0.724744721864145,
    "over_18": false,
    "stickied": false,
    "comments": 65
  },
  {
    "id": "r28oykj",
    "title": "GME dip - perfect entry point?",
    "author": "user_6530",
    "subreddit": "stocks",
    "score": 880,
    "num_comments": 298,
    "created_utc": 1759064734.1687126,
    "url": "https://reddit.com/r/stocks/",
    "timestamp": "2025-09-28T21:16:41.169072+00:00",
    "selftext": "Demo analysis for GME. This is fallback data - click to visit r/stocks.",
    "upvote_ratio": 0.7437132527546018,
    "over_18": false,
    "stickied": false,
    "comments": 194
  },
  {
    "id": "8ygq4lb",
    "title": "My MSFT position is printing \ud83d\udcb0",
    "author": "user_7310",
    "subreddit": "wallstreetbets",
    "score": 647,
    "num_comments": 151,
    "created_utc": 1759059372.1687126,
    "url": "https://reddit.com/r/wallstreetbets/",
    "timestamp": "2025-09-28T21:16:41.168828+00:00",
    "selftext": "Demo analysis for MSFT. This is fallback data - click to visit r/wallstreetbets.",
    "upvote_ratio": 0.7570359751378354,
    "over_18": false,
    "stickied": false,
    "comments": 239
  },
  {
    "id": "bvfvxo8",
    "title": "Technical analysis: AMC breakout incoming",
    "author": "user_3109",
    "subreddit": "investing",
    "score": 459,
    "num_comments": 171,
    "created_utc": 1759062969.1687126,
    "url": "https://reddit.com/r/investing/",
    "timestamp": "2025-09-28T21:16:41.168876+00:00",
    "selftext": "Demo analysis for AMC. This is fallback data - click to visit r/investing.",
    "upvote_ratio": 0.8492916696866015,
    "over_18": false,
    "stickied": false,
    "comments": 107
  },
  {
    "id": "5jk69bj",
    "title": "Hold or sell TSLA? Need advice",
    "author": "user_7811",
    "subreddit": "wallstreetbets",
    "score": 411,
    "num_comments": 69,
    "created_utc": 1759054927.1687126,
    "url": "https://reddit.com/r/wallstreetbets/",
    "timestamp": "2025-09-28T21:16:41.168909+00:00",
    "selftext": "Demo analysis for TSLA. This is fallback data - click to visit r/wallstreetbets.",
    "upvote_ratio": 0.9242599906230962,
    "over_18": false,
    "stickied": false,
    "comments": 150
  },
  {
    "id": "252qhm0",
    "title": "Hold or sell MSFT? Need advice",
    "author": "user_4828",
    "subreddit": "stocks",
    "score": 395,
    "num_comments": 120,
    "created_utc": 1759069707.1687126,
    "url": "https://reddit.com/r/stocks/",
    "timestamp": "2025-09-28T21:16:41.168931+00:00",
    "selftext": "Demo analysis for MSFT. This is fallback data - click to visit r/stocks.",
    "upvote_ratio": 0.9278010005856943,
    "over_18": false,
    "stickied": false,
    "comments": 74
  }
]