[
  {
    "id": "n8zvlow",
    "title": "My SPY position is printing \ud83d\udcb0",
    "author": "user_2718",
    "subreddit": "wallstreetbets",
    "score": 2466,
    "num_comments": 207,
    "created_utc": 1761770838.1036587,
    "url": "https://reddit.com/r/wallstreetbets/",
    "timestamp": "2025-10-30T08:28:22.104176+00:00",
    "selftext": "Demo analysis for SPY. This is fallback data - click to visit r/wallstreetbets.",
    "upvote_ratio": 0.8436491038758254,
    "over_18": false,
    "stickied": false,
    "comments": 128
  },
  {
    "id": "7z0ekc0",
    "title": "My TSLA position is printing \ud83d\udcb0",
    "author": "user_7268",
    "subreddit": "investing",
    "score": 2303,
    "num_comments": 112,
    "created_utc": 1761798591.1036587,
    "url": "https://reddit.com/r/investing/",
    "timestamp": "2025-10-30T08:28:22.103747+00:00",
    "selftext": "Demo analysis for TSLA. This is fallback data - click to visit r/investing.",
    "upvote_ratio": 0.711118757802807,
    "over_18": false,
    "stickied": false,
    "comments": 286
  },
  {
    "id": "hagdb4w",
    "title": "MSFT short squeeze potential?",
    "author": "user_4954",
    "subreddit": "investing",
    "score": 2272,
    "num_comments": 184,
    "created_utc": 1761783849.1036587,
    "url": "https://reddit.com/r/investing/",
    "timestamp": "2025-10-30T08:28:22.103702+00:00",
    "selftext": "Demo analysis for MSFT. This is fallback data - click to visit r/investing.",
    "upvote_ratio": 0.8180059839333274,
    "over_18": false,
    "stickied": false,
    "comments": 91
  },
  {
    "id": "gl6dd5e",
    "title": "META short squeeze potential?",
    "author": "user_6392",
    "subreddit": "stocks",
    "score": 2073,
    "num_comments": 66,
    "created_utc": 1761806600.1036587,
    "url": "https://reddit.com/r/stocks/",
    "timestamp": "2025-10-30T08:28:22.104129+00:00",
    "selftext": "Demo analysis for META. This is fallback data - click to visit r/stocks.",
    "upvote_ratio": 0.9193309656772328,
    "over_18": false,
    "stickied": false,
    "comments": 292
  },
  {
    "id": "qc0g3un",
    "title": "\ud83d\ude80 GME to the moon! DD inside",
    "author": "user_4896",
    "subreddit": "stocks",
    "score": 1920,
    "num_comments": 286,
    "created_utc": 1761800767.1036587,
    "url": "https://reddit.com/r/stocks/",
    "timestamp": "2025-10-30T08:28:22.103857+00:00",
    "selftext": "Demo analysis for GME. This is fallback data - click to visit r/stocks.",
    "upvote_ratio": 0.8419723977617474,
    "over_18": false,
    "stickied": false,
    "comments": 85
  },
  {
    "id": "5mf9hl2",
    "title": "MSFT short squeeze potential?",
    "author": "user_3228",
    "subreddit": "wallstreetbets",
    "score": 1895,
    "num_comments": 131,
    "created_utc": 1761806756.1036587,
    "url": "https://reddit.com/r/wallstreetbets/",
    "timestamp": "2025-10-30T08:28:22.103816+00:00",
    "selftext": "Demo analysis for MSFT. This is fallback data - click to visit r/wallstreetbets.",
    "upvote_ratio": 0.8713367010066019,
    "over_18": false,
    "stickied": false,
    "comments": 151
  },
  {
    "id": "xjwi886",
    "title": "MSFT dip - perfect entry point?",
    "author": "user_9392",
    "subreddit": "wallstreetbets",
    "score": 1776,
    "num_comments": 198,
    "created_utc": 1761778447.1036587,
    "url": "https://reddit.com/r/wallstreetbets/",
    "timestamp": "2025-10-30T08:28:22.104018+00:00",
    "selftext": "Demo analysis for MSFT. This is fallback data - click to visit r/wallstreetbets.",
    "upvote_ratio": 0.8151505232359901,
    "over_18": false,
    "stickied": false,
    "comments": 224
  },
  {
    "id": "cib66bg",
    "title": "META earnings beat expectations - bullish outlook",
    "author": "user_9739",
    "subreddit": "stocks",
    "score": 1681,
    "num_comments": 270,
    "created_utc": 1761785020.1036587,
    "url": "https://reddit.com/r/stocks/",
    "timestamp": "2025-10-30T08:28:22.104111+00:00",
    "selftext": "Demo analysis for META. This is fallback data - click to visit r/stocks.",
    "upvote_ratio": 0.8524384032149136,
    "over_18": false,
    "stickied": false,
    "comments": 276
  },
  {
    "id": "1y0qgda",
    "title": "NVDA short squeeze potential?",
    "author": "user_9183",
    "subreddit": "stocks",
    "score": 1599,
    "num_comments": 269,
    "created_utc": 1761786067.1036587,
    "url": "https://reddit.com/r/stocks/",
    "timestamp": "2025-10-30T08:28:22.103772+00:00",
    "selftext": "Demo analysis for NVDA. This is fallback data - click to visit r/stocks.",
    "upvote_ratio": 0.9413325196441599,
    "over_18": false,
    "stickied": false,
    "comments": 273
  },
  {
    "id": "l5kt01x",
    "title": "Bought 1000 shares of AMC - YOLO",
    "author": "user_1618",
    "subreddit": "stocks",
    "score": 1596,
    "num_comments": 45,
    "created_utc": 1761808707.1036587,
    "url": "https://reddit.com/r/stocks/",
    "timestamp": "2025-10-30T08:28:22.103959+00:00",
    "selftext": "Demo analysis for AMC. This is fallback data - click to visit r/stocks.",
    "upvote_ratio": 0.7568527151144927,
    "over_18": false,
    "stickied": false,
    "comments": 155
  },
  {
    "id": "p8ibu2o",
    "title": "AAPL earnings beat expectations - bullish outlook",
    "author": "user_5009",
    "subreddit": "stocks",
    "score": 1508,
    "num_comments": 256,
    "created_utc": 1761801663.1036587,
    "url": "https://reddit.com/r/stocks/",
    "timestamp": "2025-10-30T08:28:22.103940+00:00",
    "selftext": "Demo analysis for AAPL. This is fallback data - click to visit r/stocks.",
    "upvote_ratio": 0.8131190908445958,
    "over_18": false,
    "stickied": false,
    "comments": 105
  },
  {
    "id": "adaxsp3",
    "title": "Technical analysis: TSLA breakout incoming",
    "author": "user_9571",
    "subreddit": "wallstreetbets",
    "score": 1475,
    "num_comments": 89,
    "created_utc": 1761802806.1036587,
    "url": "https://reddit.com/r/wallstreetbets/",
    "timestamp": "2025-10-30T08:28:22.103920+00:00",
    "selftext": "Demo analysis for TSLA. This is fallback data - click to visit r/wallstreetbets.",
    "upvote_ratio": 0.8501544247071275,
    "over_18": false,
    "stickied": false,
    "comments": 146
  },
  {
    "id": "brx6xjz",
    "title": "SPY news catalyst could spark rally",
    "author": "user_2560",
    "subreddit": "stocks",
    "score": 1466,
    "num_comments": 130,
    "created_utc": 1761800575.1036587,
    "url": "https://reddit.com/r/stocks/",
    "timestamp": "2025-10-30T08:28:22.103878+00:00",
    "selftext": "Demo analysis for SPY. This is fallback data - click to visit r/stocks.",
    "upvote_ratio": 0.8185838747680092,
    "over_18": false,
    "stickied": false,
    "comments": 115
  },
  {
    "id": "5kzrz72",
    "title": "MSFT news catalyst could spark rally",
    "author": "user_2198",
    "subreddit": "investing",
    "score": 1260,
    "num_comments": 282,
    "created_utc": 1761807806.1036587,
    "url": "https://reddit.com/r/investing/",
    "timestamp": "2025-10-30T08:28:22.104093+00:00",
    "selftext": "Demo analysis for MSFT. This is fallback data - click to visit r/investing.",
    "upvote_ratio": 0.7334859431116639,
    "over_18": false,
    "stickied": false,
    "comments": 196
  },
  {
    "id": "7g6244m",
    "title": "My GME position is printing \ud83d\udcb0",
    "author": "user_7781",
    "subreddit": "stocks",
    "score": 1232,
    "num_comments": 237,
    "created_utc": 1761806888.1036587,
    "url": "https://reddit.com/r/stocks/",
    "timestamp": "2025-10-30T08:28:22.103796+00:00",
    "selftext": "Demo analysis for GME. This is fallback data - click to visit r/stocks.",
    "upvote_ratio": 0.7114861690069355,
    "over_18": false,
    "stickied": false,
    "comments": 42
  },
  {
    "id": "a3l6bty",
    "title": "Why NVDA is the play of the decade",
    "author": "user_4577",
    "subreddit": "wallstreetbets",
    "score": 1214,
    "num_comments": 292,
    "created_utc": 1761798054.1036587,
    "url": "https://reddit.com/r/wallstreetbets/",
    "timestamp": "2025-10-30T08:28:22.103979+00:00",
    "selftext": "Demo analysis for NVDA. This is fallback data - click to visit r/wallstreetbets.",
    "upvote_ratio": 0.8081577003435738,
    "over_18": false,
    "stickied": false,
    "comments": 215
  },
  {
    "id": "swycbna",
    "title": "SPY short squeeze potential?",
    "author": "user_4038",
    "subreddit": "investing",
    "score": 971,
    "num_comments": 272,
    "created_utc": 1761796441.1036587,
    "url": "https://reddit.com/r/investing/",
    "timestamp": "2025-10-30T08:28:22.104056+00:00",
    "selftext": "Demo analysis for SPY. This is fallback data - click to visit r/investing.",
    "upvote_ratio": 0.8251552823880395,
    "over_18": false,
    "stickied": false,
    "comments": 286
  },
  {
    "id": "ynmdne5",
    "title": "Bought 1000 shares of SPY - YOLO",
    "author": "user_8700",
    "subreddit": "stocks",
    "score": 971,
    "num_comments": 216,
    "created_utc": 1761812476.1036587,
    "url": "https://reddit.com/r/stocks/",
    "timestamp": "2025-10-30T08:28:22.104075+00:00",
    "selftext": "Demo analysis for SPY. This is fallback data - click to visit r/stocks.",
    "upvote_ratio": 0.8770623691872027,
    "over_18": false,
    "stickied": false,
    "comments": 159
  },
  {
    "id": "m8asiw0",
    "title": "MSFT short squeeze potential?",
    "author": "user_3371",
    "subreddit": "stocks",
    "score": 966,
    "num_comments": 165,
    "created_utc": 1761796156.1036587,
    "url": "https://reddit.com/r/stocks/",
    "timestamp": "2025-10-30T08:28:22.104151+00:00",
    "selftext": "Demo analysis for MSFT. This is fallback data - click to visit r/stocks.",
    "upvote_ratio": 0.8982923181647633,
    "over_18": false,
    "stickied": false,
    "comments": 163
  },
  {
    "id": "f0cnyeh",
    "title": "Why AMC is the play of the decade",
    "author": "user_6464",
    "subreddit": "stocks",
    "score": 846,
    "num_comments": 257,
    "created_utc": 1761796418.1036587,
    "url": "https://reddit.com/r/stocks/",
    "timestamp": "2025-10-30T08:28:22.103899+00:00",
    "selftext": "Demo analysis for AMC. This is fallback data - click to visit r/stocks.",
    "upvote_ratio": 0.7441179363701794,
    "over_18": false,
    "stickied": false,
    "comments": 232
  },
  {
    "id": "ncibb5e",
    "title": "Hold or sell NVDA? Need advice",
    "author": "user_8635",
    "subreddit": "wallstreetbets",
    "score": 842,
    "num_comments": 82,
    "created_utc": 1761771609.1036587,
    "url": "https://reddit.com/r/wallstreetbets/",
    "timestamp": "2025-10-30T08:28:22.104037+00:00",
    "selftext": "Demo analysis for NVDA. This is fallback data - click to visit r/wallstreetbets.",
    "upvote_ratio": 0.788753160189937,
    "over_18": false,
    "stickied": false,
    "comments": 133
  },
  {
    "id": "qtiwdj1",
    "title": "Technical analysis: AMC breakout incoming",
    "author": "user_7115",
    "subreddit": "stocks",
    "score": 828,
    "num_comments": 146,
    "created_utc": 1761779370.1036587,
    "url": "https://reddit.com/r/stocks/",
    "timestamp": "2025-10-30T08:28:22.103838+00:00",
    "selftext": "Demo analysis for AMC. This is fallback data - click to visit r/stocks.",
    "upvote_ratio": 0.8673953478115658,
    "over_18": false,
    "stickied": false,
    "comments": 182
  },
  {
    "id": "ax24n17",
    "title": "AMZN dip - perfect entry point?",
    "author": "user_6144",
    "subreddit": "stocks",
    "score": 630,
    "num_comments": 38,
    "created_utc": 1761770116.1036587,
    "url": "https://reddit.com/r/stocks/",
    "timestamp": "2025-10-30T08:28:22.104163+00:00",
    "selftext": "Demo analysis for AMZN. This is fallback data - click to visit r/stocks.",
    "upvote_ratio": 0.7115335699434194,
    "over_18": false,
    "stickied": false,
    "comments": 40
  },
  {
    "id": "icv4y2c",
    "title": "Technical analysis: META breakout incoming",
    "author": "user_3530",
    "subreddit": "investing",
    "score": 600,
    "num_comments": 88,
    "created_utc": 1761770207.1036587,
    "url": "https://reddit.com/r/investing/",
    "timestamp": "2025-10-30T08:28:22.103999+00:00",
    "selftext": "Demo analysis for META. This is fallback data - click to visit r/investing.",
    "upvote_ratio": 0.8450003687549155,
    "over_18": false,
    "stickied": false,
    "comments": 220
  },
  {
    "id": "be4o0vd",
    "title": "Bought 1000 shares of AMC - YOLO",
    "author": "user_4576",
    "subreddit": "stocks",
    "score": 397,
    "num_comments": 104,
    "created_utc": 1761790674.1036587,
    "url": "https://reddit.com/r/stocks/",
    "timestamp": "2025-10-30T08:28:22.104188+00:00",
    "selftext": "Demo analysis for AMC. This is fallback data - click to visit r/stocks.",
    "upvote_ratio": 0.8914316583336214,
    "over_18": false,
    "stickied": false,
    "comments": 160
  }
]