[
  {
    "id": "0n92sxe",
    "title": "\ud83d\ude80 AMZN to the moon! DD inside",
    "author": "user_6638",
    "subreddit": "wallstreetbets",
    "score": 2343,
    "num_comments": 290,
    "created_utc": 1775409934.4439638,
    "url": "https://reddit.com/r/wallstreetbets/",
    "timestamp": "2026-04-05T17:34:50.444511+00:00",
    "selftext": "Demo analysis for AMZN. This is fallback data - click to visit r/wallstreetbets.",
    "upvote_ratio": 0.9367134362029653,
    "over_18": false,
    "stickied": false,
    "comments": 118
  },
  {
    "id": "z1fn2fw",
    "title": "My TSLA position is printing \ud83d\udcb0",
    "author": "user_8368",
    "subreddit": "investing",
    "score": 2294,
    "num_comments": 62,
    "created_utc": 1775378409.4439638,
    "url": "https://reddit.com/r/investing/",
    "timestamp": "2026-04-05T17:34:50.444399+00:00",
    "selftext": "Demo analysis for TSLA. This is fallback data - click to visit r/investing.",
    "upvote_ratio": 0.7278375462241407,
    "over_18": false,
    "stickied": false,
    "comments": 24
  },
  {
    "id": "x6dsyuh",
    "title": "Technical analysis: AMC breakout incoming",
    "author": "user_3096",
    "subreddit": "stocks",
    "score": 2266,
    "num_comments": 271,
    "created_utc": 1775392762.4439638,
    "url": "https://reddit.com/r/stocks/",
    "timestamp": "2026-04-05T17:34:50.444175+00:00",
    "selftext": "Demo analysis for AMC. This is fallback data - click to visit r/stocks.",
    "upvote_ratio": 0.7663268270732866,
    "over_18": false,
    "stickied": false,
    "comments": 251
  },
  {
    "id": "dy2ttot",
    "title": "Bought 1000 shares of NVDA - YOLO",
    "author": "user_4622",
    "subreddit": "wallstreetbets",
    "score": 2180,
    "num_comments": 208,
    "created_utc": 1775404843.4439638,
    "url": "https://reddit.com/r/wallstreetbets/",
    "timestamp": "2026-04-05T17:34:50.444499+00:00",
    "selftext": "Demo analysis for NVDA. This is fallback data - click to visit r/wallstreetbets.",
    "upvote_ratio": 0.9293763893836936,
    "over_18": false,
    "stickied": false,
    "comments": 102
  },
  {
    "id": "gt9isrt",
    "title": "Why TSLA is the play of the decade",
    "author": "user_6569",
    "subreddit": "wallstreetbets",
    "score": 2116,
    "num_comments": 261,
    "created_utc": 1775385107.4439638,
    "url": "https://reddit.com/r/wallstreetbets/",
    "timestamp": "2026-04-05T17:34:50.444094+00:00",
    "selftext": "Demo analysis for TSLA. This is fallback data - click to visit r/wallstreetbets.",
    "upvote_ratio": 0.8176756457735037,
    "over_18": false,
    "stickied": false,
    "comments": 99
  },
  {
    "id": "7e04s9f",
    "title": "Technical analysis: META breakout incoming",
    "author": "user_1206",
    "subreddit": "stocks",
    "score": 1970,
    "num_comments": 284,
    "created_utc": 1775375404.4439638,
    "url": "https://reddit.com/r/stocks/",
    "timestamp": "2026-04-05T17:34:50.444243+00:00",
    "selftext": "Demo analysis for META. This is fallback data - click to visit r/stocks.",
    "upvote_ratio": 0.7334738643099092,
    "over_18": false,
    "stickied": false,
    "comments": 37
  },
  {
    "id": "bggcfkm",
    "title": "AAPL earnings beat expectations - bullish outlook",
    "author": "user_7486",
    "subreddit": "investing",
    "score": 1898,
    "num_comments": 191,
    "created_utc": 1775385015.4439638,
    "url": "https://reddit.com/r/investing/",
    "timestamp": "2026-04-05T17:34:50.444006+00:00",
    "selftext": "Demo analysis for AAPL. This is fallback data - click to visit r/investing.",
    "upvote_ratio": 0.7373097514797229,
    "over_18": false,
    "stickied": false,
    "comments": 217
  },
  {
    "id": "j73abe0",
    "title": "Bought 1000 shares of META - YOLO",
    "author": "user_1349",
    "subreddit": "wallstreetbets",
    "score": 1886,
    "num_comments": 261,
    "created_utc": 1775376391.4439638,
    "url": "https://reddit.com/r/wallstreetbets/",
    "timestamp": "2026-04-05T17:34:50.444050+00:00",
    "selftext": "Demo analysis for META. This is fallback data - click to visit r/wallstreetbets.",
    "upvote_ratio": 0.8218465101825395,
    "over_18": false,
    "stickied": false,
    "comments": 92
  },
  {
    "id": "tkuptnn",
    "title": "Bought 1000 shares of TSLA - YOLO",
    "author": "user_8414",
    "subreddit": "wallstreetbets",
    "score": 1846,
    "num_comments": 122,
    "created_utc": 1775404246.4439638,
    "url": "https://reddit.com/r/wallstreetbets/",
    "timestamp": "2026-04-05T17:34:50.444074+00:00",
    "selftext": "Demo analysis for TSLA. This is fallback data - click to visit r/wallstreetbets.",
    "upvote_ratio": 0.8136445416071129,
    "over_18": false,
    "stickied": false,
    "comments": 33
  },
  {
    "id": "tpuldv3",
    "title": "My AMC position is printing \ud83d\udcb0",
    "author": "user_3020",
    "subreddit": "wallstreetbets",
    "score": 1686,
    "num_comments": 66,
    "created_utc": 1775387563.4439638,
    "url": "https://reddit.com/r/wallstreetbets/",
    "timestamp": "2026-04-05T17:34:50.444488+00:00",
    "selftext": "Demo analysis for AMC. This is fallback data - click to visit r/wallstreetbets.",
    "upvote_ratio": 0.8083268727073747,
    "over_18": false,
    "stickied": false,
    "comments": 223
  },
  {
    "id": "3f37otb",
    "title": "META news catalyst could spark rally",
    "author": "user_1613",
    "subreddit": "stocks",
    "score": 1663,
    "num_comments": 138,
    "created_utc": 1775379148.4439638,
    "url": "https://reddit.com/r/stocks/",
    "timestamp": "2026-04-05T17:34:50.444417+00:00",
    "selftext": "Demo analysis for META. This is fallback data - click to visit r/stocks.",
    "upvote_ratio": 0.8852725344769595,
    "over_18": false,
    "stickied": false,
    "comments": 222
  },
  {
    "id": "th5rpj1",
    "title": "TSLA news catalyst could spark rally",
    "author": "user_1226",
    "subreddit": "investing",
    "score": 1232,
    "num_comments": 44,
    "created_utc": 1775396332.4439638,
    "url": "https://reddit.com/r/investing/",
    "timestamp": "2026-04-05T17:34:50.444302+00:00",
    "selftext": "Demo analysis for TSLA. This is fallback data - click to visit r/investing.",
    "upvote_ratio": 0.904244912262759,
    "over_18": false,
    "stickied": false,
    "comments": 300
  },
  {
    "id": "pxztxqe",
    "title": "MSFT dip - perfect entry point?",
    "author": "user_6657",
    "subreddit": "investing",
    "score": 1157,
    "num_comments": 245,
    "created_utc": 1775368812.4439638,
    "url": "https://reddit.com/r/investing/",
    "timestamp": "2026-04-05T17:34:50.444455+00:00",
    "selftext": "Demo analysis for MSFT. This is fallback data - click to visit r/investing.",
    "upvote_ratio": 0.7213654981099666,
    "over_18": false,
    "stickied": false,
    "comments": 137
  },
  {
    "id": "9fduch5",
    "title": "GME earnings beat expectations - bullish outlook",
    "author": "user_3597",
    "subreddit": "investing",
    "score": 1060,
    "num_comments": 285,
    "created_utc": 1775386596.4439638,
    "url": "https://reddit.com/r/investing/",
    "timestamp": "2026-04-05T17:34:50.444521+00:00",
    "selftext": "Demo analysis for GME. This is fallback data - click to visit r/investing.",
    "upvote_ratio": 0.8171981543436649,
    "over_18": false,
    "stickied": false,
    "comments": 192
  },
  {
    "id": "290gpmh",
    "title": "\ud83d\ude80 AAPL to the moon! DD inside",
    "author": "user_5000",
    "subreddit": "investing",
    "score": 959,
    "num_comments": 157,
    "created_utc": 1775385637.4439638,
    "url": "https://reddit.com/r/investing/",
    "timestamp": "2026-04-05T17:34:50.444322+00:00",
    "selftext": "Demo analysis for AAPL. This is fallback data - click to visit r/investing.",
    "upvote_ratio": 0.9490470780832757,
    "over_18": false,
    "stickied": false,
    "comments": 37
  },
  {
    "id": "praewtb",
    "title": "GME news catalyst could spark rally",
    "author": "user_3495",
    "subreddit": "wallstreetbets",
    "score": 872,
    "num_comments": 91,
    "created_utc": 1775394131.4439638,
    "url": "https://reddit.com/r/wallstreetbets/",
    "timestamp": "2026-04-05T17:34:50.444263+00:00",
    "selftext": "Demo analysis for GME. This is fallback data - click to visit r/wallstreetbets.",
    "upvote_ratio": 0.9393336053291563,
    "over_18": false,
    "stickied": false,
    "comments": 203
  },
  {
    "id": "lnmaptg",
    "title": "GOOGL short squeeze potential?",
    "author": "user_9271",
    "subreddit": "wallstreetbets",
    "score": 836,
    "num_comments": 166,
    "created_utc": 1775407836.4439638,
    "url": "https://reddit.com/r/wallstreetbets/",
    "timestamp": "2026-04-05T17:34:50.444149+00:00",
    "selftext": "Demo analysis for GOOGL. This is fallback data - click to visit r/wallstreetbets.",
    "upvote_ratio": 0.8277937707893024,
    "over_18": false,
    "stickied": false,
    "comments": 44
  },
  {
    "id": "urrovb0",
    "title": "AMZN earnings beat expectations - bullish outlook",
    "author": "user_8413",
    "subreddit": "stocks",
    "score": 822,
    "num_comments": 160,
    "created_utc": 1775379345.4439638,
    "url": "https://reddit.com/r/stocks/",
    "timestamp": "2026-04-05T17:34:50.444476+00:00",
    "selftext": "Demo analysis for AMZN. This is fallback data - click to visit r/stocks.",
    "upvote_ratio": 0.9433011124493198,
    "over_18": false,
    "stickied": false,
    "comments": 51
  },
  {
    "id": "1opkoq3",
    "title": "My TSLA position is printing \ud83d\udcb0",
    "author": "user_4962",
    "subreddit": "stocks",
    "score": 784,
    "num_comments": 207,
    "created_utc": 1775396178.4439638,
    "url": "https://reddit.com/r/stocks/",
    "timestamp": "2026-04-05T17:34:50.444360+00:00",
    "selftext": "Demo analysis for TSLA. This is fallback data - click to visit r/stocks.",
    "upvote_ratio": 0.9434227626900034,
    "over_18": false,
    "stickied": false,
    "comments": 193
  },
  {
    "id": "gunm99c",
    "title": "My TSLA position is printing \ud83d\udcb0",
    "author": "user_7387",
    "subreddit": "stocks",
    "score": 745,
    "num_comments": 98,
    "created_utc": 1775389382.4439638,
    "url": "https://reddit.com/r/stocks/",
    "timestamp": "2026-04-05T17:34:50.444222+00:00",
    "selftext": "Demo analysis for TSLA. This is fallback data - click to visit r/stocks.",
    "upvote_ratio": 0.7902076176273167,
    "over_18": false,
    "stickied": false,
    "comments": 216
  },
  {
    "id": "3ei19l7",
    "title": "Why GOOGL is the play of the decade",
    "author": "user_8602",
    "subreddit": "stocks",
    "score": 556,
    "num_comments": 20,
    "created_utc": 1775384234.4439638,
    "url": "https://reddit.com/r/stocks/",
    "timestamp": "2026-04-05T17:34:50.444340+00:00",
    "selftext": "Demo analysis for GOOGL. This is fallback data - click to visit r/stocks.",
    "upvote_ratio": 0.9381309918051823,
    "over_18": false,
    "stickied": false,
    "comments": 198
  },
  {
    "id": "gn3hzre",
    "title": "MSFT news catalyst could spark rally",
    "author": "user_4185",
    "subreddit": "stocks",
    "score": 547,
    "num_comments": 230,
    "created_utc": 1775368203.4439638,
    "url": "https://reddit.com/r/stocks/",
    "timestamp": "2026-04-05T17:34:50.444380+00:00",
    "selftext": "Demo analysis for MSFT. This is fallback data - click to visit r/stocks.",
    "upvote_ratio": 0.9283411893305645,
    "over_18": false,
    "stickied": false,
    "comments": 48
  },
  {
    "id": "tosiyll",
    "title": "Bought 1000 shares of GOOGL - YOLO",
    "author": "user_8553",
    "subreddit": "investing",
    "score": 496,
    "num_comments": 197,
    "created_utc": 1775405854.4439638,
    "url": "https://reddit.com/r/investing/",
    "timestamp": "2026-04-05T17:34:50.444196+00:00",
    "selftext": "Demo analysis for GOOGL. This is fallback data - click to visit r/investing.",
    "upvote_ratio": 0.7281831595521997,
    "over_18": false,
    "stickied": false,
    "comments": 56
  },
  {
    "id": "be9bfdy",
    "title": "SPY earnings beat expectations - bullish outlook",
    "author": "user_6796",
    "subreddit": "investing",
    "score": 484,
    "num_comments": 245,
    "created_utc": 1775369469.4439638,
    "url": "https://reddit.com/r/investing/",
    "timestamp": "2026-04-05T17:34:50.444282+00:00",
    "selftext": "Demo analysis for SPY. This is fallback data - click to visit r/investing.",
    "upvote_ratio": 0.9461938567098878,
    "over_18": false,
    "stickied": false,
    "comments": 164
  },
  {
    "id": "h02fh4e",
    "title": "Why META is the play of the decade",
    "author": "user_9168",
    "subreddit": "stocks",
    "score": 386,
    "num_comments": 207,
    "created_utc": 1775407417.4439638,
    "url": "https://reddit.com/r/stocks/",
    "timestamp": "2026-04-05T17:34:50.444435+00:00",
    "selftext": "Demo analysis for META. This is fallback data - click to visit r/stocks.",
    "upvote_ratio": 0.9496077801490941,
    "over_18": false,
    "stickied": false,
    "comments": 167
  }
]