[
  {
    "id": "jopxsgs",
    "title": "Hold or sell AMZN? Need advice",
    "author": "user_5926",
    "subreddit": "stocks",
    "score": 2453,
    "num_comments": 270,
    "created_utc": 1759974770.9778914,
    "url": "https://reddit.com/r/stocks/",
    "timestamp": "2025-10-09T05:20:05.978086+00:00",
    "selftext": "Demo analysis for AMZN. This is fallback data - click to visit r/stocks.",
    "upvote_ratio": 0.9297734933691071,
    "over_18": false,
    "stickied": false,
    "comments": 178
  },
  {
    "id": "rnraaiw",
    "title": "\ud83d\ude80 GME to the moon! DD inside",
    "author": "user_5912",
    "subreddit": "stocks",
    "score": 2421,
    "num_comments": 281,
    "created_utc": 1759959960.9778914,
    "url": "https://reddit.com/r/stocks/",
    "timestamp": "2025-10-09T05:20:05.977932+00:00",
    "selftext": "Demo analysis for GME. This is fallback data - click to visit r/stocks.",
    "upvote_ratio": 0.870418621857726,
    "over_18": false,
    "stickied": false,
    "comments": 104
  },
  {
    "id": "isv0euc",
    "title": "Why NVDA is the play of the decade",
    "author": "user_1190",
    "subreddit": "wallstreetbets",
    "score": 2409,
    "num_comments": 250,
    "created_utc": 1759979876.9778914,
    "url": "https://reddit.com/r/wallstreetbets/",
    "timestamp": "2025-10-09T05:20:05.978075+00:00",
    "selftext": "Demo analysis for NVDA. This is fallback data - click to visit r/wallstreetbets.",
    "upvote_ratio": 0.8065637059668281,
    "over_18": false,
    "stickied": false,
    "comments": 290
  },
  {
    "id": "xvph41z",
    "title": "Technical analysis: GME breakout incoming",
    "author": "user_6360",
    "subreddit": "wallstreetbets",
    "score": 2375,
    "num_comments": 144,
    "created_utc": 1759964718.9778914,
    "url": "https://reddit.com/r/wallstreetbets/",
    "timestamp": "2025-10-09T05:20:05.978119+00:00",
    "selftext": "Demo analysis for GME. This is fallback data - click to visit r/wallstreetbets.",
    "upvote_ratio": 0.8998220354122282,
    "over_18": false,
    "stickied": false,
    "comments": 54
  },
  {
    "id": "5052xiy",
    "title": "Technical analysis: AMC breakout incoming",
    "author": "user_6762",
    "subreddit": "wallstreetbets",
    "score": 2361,
    "num_comments": 238,
    "created_utc": 1759961239.9778914,
    "url": "https://reddit.com/r/wallstreetbets/",
    "timestamp": "2025-10-09T05:20:05.978194+00:00",
    "selftext": "Demo analysis for AMC. This is fallback data - click to visit r/wallstreetbets.",
    "upvote_ratio": 0.8538824247513294,
    "over_18": false,
    "stickied": false,
    "comments": 153
  },
  {
    "id": "634p6hx",
    "title": "\ud83d\ude80 NVDA to the moon! DD inside",
    "author": "user_1978",
    "subreddit": "investing",
    "score": 2279,
    "num_comments": 300,
    "created_utc": 1759958248.9778914,
    "url": "https://reddit.com/r/investing/",
    "timestamp": "2025-10-09T05:20:05.978151+00:00",
    "selftext": "Demo analysis for NVDA. This is fallback data - click to visit r/investing.",
    "upvote_ratio": 0.8724062184603221,
    "over_18": false,
    "stickied": false,
    "comments": 182
  },
  {
    "id": "qx7xysr",
    "title": "Why SPY is the play of the decade",
    "author": "user_2350",
    "subreddit": "stocks",
    "score": 2187,
    "num_comments": 29,
    "created_utc": 1759971933.9778914,
    "url": "https://reddit.com/r/stocks/",
    "timestamp": "2025-10-09T05:20:05.978129+00:00",
    "selftext": "Demo analysis for SPY. This is fallback data - click to visit r/stocks.",
    "upvote_ratio": 0.8306401840151713,
    "over_18": false,
    "stickied": false,
    "comments": 228
  },
  {
    "id": "o4oxruz",
    "title": "GOOGL news catalyst could spark rally",
    "author": "user_7967",
    "subreddit": "stocks",
    "score": 1921,
    "num_comments": 289,
    "created_utc": 1759964449.9778914,
    "url": "https://reddit.com/r/stocks/",
    "timestamp": "2025-10-09T05:20:05.978173+00:00",
    "selftext": "Demo analysis for GOOGL. This is fallback data - click to visit r/stocks.",
    "upvote_ratio": 0.7068455760740839,
    "over_18": false,
    "stickied": false,
    "comments": 253
  },
  {
    "id": "iceso04",
    "title": "Bought 1000 shares of MSFT - YOLO",
    "author": "user_2396",
    "subreddit": "wallstreetbets",
    "score": 1905,
    "num_comments": 35,
    "created_utc": 1759951577.9778914,
    "url": "https://reddit.com/r/wallstreetbets/",
    "timestamp": "2025-10-09T05:20:05.978064+00:00",
    "selftext": "Demo analysis for MSFT. This is fallback data - click to visit r/wallstreetbets.",
    "upvote_ratio": 0.9296063820705196,
    "over_18": false,
    "stickied": false,
    "comments": 51
  },
  {
    "id": "l10qcgp",
    "title": "Hold or sell NVDA? Need advice",
    "author": "user_3041",
    "subreddit": "stocks",
    "score": 1845,
    "num_comments": 238,
    "created_utc": 1759968366.9778914,
    "url": "https://reddit.com/r/stocks/",
    "timestamp": "2025-10-09T05:20:05.978163+00:00",
    "selftext": "Demo analysis for NVDA. This is fallback data - click to visit r/stocks.",
    "upvote_ratio": 0.9255766015676627,
    "over_18": false,
    "stickied": false,
    "comments": 248
  },
  {
    "id": "w4d425o",
    "title": "META short squeeze potential?",
    "author": "user_4118",
    "subreddit": "stocks",
    "score": 1760,
    "num_comments": 267,
    "created_utc": 1759955275.9778914,
    "url": "https://reddit.com/r/stocks/",
    "timestamp": "2025-10-09T05:20:05.977976+00:00",
    "selftext": "Demo analysis for META. This is fallback data - click to visit r/stocks.",
    "upvote_ratio": 0.7193058342093386,
    "over_18": false,
    "stickied": false,
    "comments": 276
  },
  {
    "id": "ijf0zyo",
    "title": "AMC news catalyst could spark rally",
    "author": "user_1440",
    "subreddit": "stocks",
    "score": 1601,
    "num_comments": 72,
    "created_utc": 1759955178.9778914,
    "url": "https://reddit.com/r/stocks/",
    "timestamp": "2025-10-09T05:20:05.978003+00:00",
    "selftext": "Demo analysis for AMC. This is fallback data - click to visit r/stocks.",
    "upvote_ratio": 0.8282087650230789,
    "over_18": false,
    "stickied": false,
    "comments": 204
  },
  {
    "id": "t9hkvcw",
    "title": "Hold or sell NVDA? Need advice",
    "author": "user_8481",
    "subreddit": "wallstreetbets",
    "score": 1416,
    "num_comments": 295,
    "created_utc": 1759954422.9778914,
    "url": "https://reddit.com/r/wallstreetbets/",
    "timestamp": "2025-10-09T05:20:05.977962+00:00",
    "selftext": "Demo analysis for NVDA. This is fallback data - click to visit r/wallstreetbets.",
    "upvote_ratio": 0.7099493534004666,
    "over_18": false,
    "stickied": false,
    "comments": 231
  },
  {
    "id": "ivn7zrn",
    "title": "META dip - perfect entry point?",
    "author": "user_4459",
    "subreddit": "wallstreetbets",
    "score": 1377,
    "num_comments": 193,
    "created_utc": 1759985886.9778914,
    "url": "https://reddit.com/r/wallstreetbets/",
    "timestamp": "2025-10-09T05:20:05.978108+00:00",
    "selftext": "Demo analysis for META. This is fallback data - click to visit r/wallstreetbets.",
    "upvote_ratio": 0.9359639737959251,
    "over_18": false,
    "stickied": false,
    "comments": 60
  },
  {
    "id": "80scaem",
    "title": "Technical analysis: GME breakout incoming",
    "author": "user_3996",
    "subreddit": "wallstreetbets",
    "score": 1286,
    "num_comments": 266,
    "created_utc": 1759951218.9778914,
    "url": "https://reddit.com/r/wallstreetbets/",
    "timestamp": "2025-10-09T05:20:05.978016+00:00",
    "selftext": "Demo analysis for GME. This is fallback data - click to visit r/wallstreetbets.",
    "upvote_ratio": 0.8560378054184538,
    "over_18": false,
    "stickied": false,
    "comments": 184
  },
  {
    "id": "w8ev137",
    "title": "GOOGL short squeeze potential?",
    "author": "user_9111",
    "subreddit": "investing",
    "score": 1138,
    "num_comments": 88,
    "created_utc": 1759973352.9778914,
    "url": "https://reddit.com/r/investing/",
    "timestamp": "2025-10-09T05:20:05.978052+00:00",
    "selftext": "Demo analysis for GOOGL. This is fallback data - click to visit r/investing.",
    "upvote_ratio": 0.7604676605879633,
    "over_18": false,
    "stickied": false,
    "comments": 187
  },
  {
    "id": "uroum7t",
    "title": "\ud83d\ude80 AAPL to the moon! DD inside",
    "author": "user_2647",
    "subreddit": "investing",
    "score": 1123,
    "num_comments": 179,
    "created_utc": 1759975476.9778914,
    "url": "https://reddit.com/r/investing/",
    "timestamp": "2025-10-09T05:20:05.978040+00:00",
    "selftext": "Demo analysis for AAPL. This is fallback data - click to visit r/investing.",
    "upvote_ratio": 0.7216832962417533,
    "over_18": false,
    "stickied": false,
    "comments": 99
  },
  {
    "id": "u5lm7le",
    "title": "Bought 1000 shares of AMZN - YOLO",
    "author": "user_6026",
    "subreddit": "wallstreetbets",
    "score": 985,
    "num_comments": 150,
    "created_utc": 1759982005.9778914,
    "url": "https://reddit.com/r/wallstreetbets/",
    "timestamp": "2025-10-09T05:20:05.978220+00:00",
    "selftext": "Demo analysis for AMZN. This is fallback data - click to visit r/wallstreetbets.",
    "upvote_ratio": 0.7126399730360807,
    "over_18": false,
    "stickied": false,
    "comments": 99
  },
  {
    "id": "80qh3ed",
    "title": "Technical analysis: AMZN breakout incoming",
    "author": "user_5547",
    "subreddit": "investing",
    "score": 929,
    "num_comments": 70,
    "created_utc": 1759948643.9778914,
    "url": "https://reddit.com/r/investing/",
    "timestamp": "2025-10-09T05:20:05.978140+00:00",
    "selftext": "Demo analysis for AMZN. This is fallback data - click to visit r/investing.",
    "upvote_ratio": 0.9472601106444873,
    "over_18": false,
    "stickied": false,
    "comments": 215
  },
  {
    "id": "ycimqb9",
    "title": "Bought 1000 shares of GME - YOLO",
    "author": "user_3986",
    "subreddit": "investing",
    "score": 806,
    "num_comments": 154,
    "created_utc": 1759961871.9778914,
    "url": "https://reddit.com/r/investing/",
    "timestamp": "2025-10-09T05:20:05.978243+00:00",
    "selftext": "Demo analysis for GME. This is fallback data - click to visit r/investing.",
    "upvote_ratio": 0.8815754550452406,
    "over_18": false,
    "stickied": false,
    "comments": 251
  },
  {
    "id": "2at9g0a",
    "title": "Hold or sell TSLA? Need advice",
    "author": "user_2843",
    "subreddit": "stocks",
    "score": 707,
    "num_comments": 256,
    "created_utc": 1759985837.9778914,
    "url": "https://reddit.com/r/stocks/",
    "timestamp": "2025-10-09T05:20:05.977990+00:00",
    "selftext": "Demo analysis for TSLA. This is fallback data - click to visit r/stocks.",
    "upvote_ratio": 0.9274207924321809,
    "over_18": false,
    "stickied": false,
    "comments": 125
  },
  {
    "id": "6q07pne",
    "title": "Why AAPL is the play of the decade",
    "author": "user_2283",
    "subreddit": "investing",
    "score": 681,
    "num_comments": 75,
    "created_utc": 1759956861.9778914,
    "url": "https://reddit.com/r/investing/",
    "timestamp": "2025-10-09T05:20:05.978184+00:00",
    "selftext": "Demo analysis for AAPL. This is fallback data - click to visit r/investing.",
    "upvote_ratio": 0.9185106013013389,
    "over_18": false,
    "stickied": false,
    "comments": 269
  },
  {
    "id": "3b88koj",
    "title": "TSLA earnings beat expectations - bullish outlook",
    "author": "user_2835",
    "subreddit": "wallstreetbets",
    "score": 451,
    "num_comments": 258,
    "created_utc": 1759968723.9778914,
    "url": "https://reddit.com/r/wallstreetbets/",
    "timestamp": "2025-10-09T05:20:05.978233+00:00",
    "selftext": "Demo analysis for TSLA. This is fallback data - click to visit r/wallstreetbets.",
    "upvote_ratio": 0.811798804660465,
    "over_18": false,
    "stickied": false,
    "comments": 239
  },
  {
    "id": "9gwd4fo",
    "title": "Bought 1000 shares of GME - YOLO",
    "author": "user_1788",
    "subreddit": "wallstreetbets",
    "score": 406,
    "num_comments": 87,
    "created_utc": 1759962863.9778914,
    "url": "https://reddit.com/r/wallstreetbets/",
    "timestamp": "2025-10-09T05:20:05.978028+00:00",
    "selftext": "Demo analysis for GME. This is fallback data - click to visit r/wallstreetbets.",
    "upvote_ratio": 0.7943763208305937,
    "over_18": false,
    "stickied": false,
    "comments": 48
  },
  {
    "id": "gncqj82",
    "title": "AMC short squeeze potential?",
    "author": "user_4335",
    "subreddit": "stocks",
    "score": 279,
    "num_comments": 235,
    "created_utc": 1759982225.9778914,
    "url": "https://reddit.com/r/stocks/",
    "timestamp": "2025-10-09T05:20:05.978098+00:00",
    "selftext": "Demo analysis for AMC. This is fallback data - click to visit r/stocks.",
    "upvote_ratio": 0.9140572977654691,
    "over_18": false,
    "stickied": false,
    "comments": 50
  }
]