[
  {
    "id": "as0otea",
    "title": "\ud83d\ude80 GME to the moon! DD inside",
    "author": "user_8260",
    "subreddit": "investing",
    "score": 2486,
    "num_comments": 291,
    "created_utc": 1771069767.4915974,
    "url": "https://reddit.com/r/investing/",
    "timestamp": "2026-02-14T22:27:10.492050+00:00",
    "selftext": "Demo analysis for GME. This is fallback data - click to visit r/investing.",
    "upvote_ratio": 0.7383274272800741,
    "over_18": false,
    "stickied": false,
    "comments": 130
  },
  {
    "id": "1ubw277",
    "title": "\ud83d\ude80 GOOGL to the moon! DD inside",
    "author": "user_5566",
    "subreddit": "stocks",
    "score": 2374,
    "num_comments": 91,
    "created_utc": 1771068797.4915974,
    "url": "https://reddit.com/r/stocks/",
    "timestamp": "2026-02-14T22:27:10.492124+00:00",
    "selftext": "Demo analysis for GOOGL. This is fallback data - click to visit r/stocks.",
    "upvote_ratio": 0.836828835564475,
    "over_18": false,
    "stickied": false,
    "comments": 89
  },
  {
    "id": "6rxlegq",
    "title": "My AMZN position is printing \ud83d\udcb0",
    "author": "user_9366",
    "subreddit": "investing",
    "score": 2227,
    "num_comments": 194,
    "created_utc": 1771092423.4915974,
    "url": "https://reddit.com/r/investing/",
    "timestamp": "2026-02-14T22:27:10.491751+00:00",
    "selftext": "Demo analysis for AMZN. This is fallback data - click to visit r/investing.",
    "upvote_ratio": 0.8191336379063423,
    "over_18": false,
    "stickied": false,
    "comments": 276
  },
  {
    "id": "fjzvw86",
    "title": "META short squeeze potential?",
    "author": "user_7811",
    "subreddit": "wallstreetbets",
    "score": 2219,
    "num_comments": 297,
    "created_utc": 1771107099.4915974,
    "url": "https://reddit.com/r/wallstreetbets/",
    "timestamp": "2026-02-14T22:27:10.491926+00:00",
    "selftext": "Demo analysis for META. This is fallback data - click to visit r/wallstreetbets.",
    "upvote_ratio": 0.7163451178581426,
    "over_18": false,
    "stickied": false,
    "comments": 69
  },
  {
    "id": "oqelxr1",
    "title": "\ud83d\ude80 META to the moon! DD inside",
    "author": "user_5722",
    "subreddit": "wallstreetbets",
    "score": 1926,
    "num_comments": 200,
    "created_utc": 1771099975.4915974,
    "url": "https://reddit.com/r/wallstreetbets/",
    "timestamp": "2026-02-14T22:27:10.491728+00:00",
    "selftext": "Demo analysis for META. This is fallback data - click to visit r/wallstreetbets.",
    "upvote_ratio": 0.732450451746055,
    "over_18": false,
    "stickied": false,
    "comments": 114
  },
  {
    "id": "55ja9bi",
    "title": "META dip - perfect entry point?",
    "author": "user_1411",
    "subreddit": "stocks",
    "score": 1916,
    "num_comments": 125,
    "created_utc": 1771105075.4915974,
    "url": "https://reddit.com/r/stocks/",
    "timestamp": "2026-02-14T22:27:10.491640+00:00",
    "selftext": "Demo analysis for META. This is fallback data - click to visit r/stocks.",
    "upvote_ratio": 0.8495735903979009,
    "over_18": false,
    "stickied": false,
    "comments": 20
  },
  {
    "id": "6hsfsvp",
    "title": "\ud83d\ude80 GOOGL to the moon! DD inside",
    "author": "user_2155",
    "subreddit": "investing",
    "score": 1671,
    "num_comments": 104,
    "created_utc": 1771095536.4915974,
    "url": "https://reddit.com/r/investing/",
    "timestamp": "2026-02-14T22:27:10.492068+00:00",
    "selftext": "Demo analysis for GOOGL. This is fallback data - click to visit r/investing.",
    "upvote_ratio": 0.9400976960187337,
    "over_18": false,
    "stickied": false,
    "comments": 80
  },
  {
    "id": "pjhuzr0",
    "title": "META earnings beat expectations - bullish outlook",
    "author": "user_7780",
    "subreddit": "stocks",
    "score": 1655,
    "num_comments": 85,
    "created_utc": 1771094772.4915974,
    "url": "https://reddit.com/r/stocks/",
    "timestamp": "2026-02-14T22:27:10.491947+00:00",
    "selftext": "Demo analysis for META. This is fallback data - click to visit r/stocks.",
    "upvote_ratio": 0.9384553812051878,
    "over_18": false,
    "stickied": false,
    "comments": 177
  },
  {
    "id": "7czyv2s",
    "title": "My NVDA position is printing \ud83d\udcb0",
    "author": "user_4761",
    "subreddit": "wallstreetbets",
    "score": 1602,
    "num_comments": 106,
    "created_utc": 1771107240.4915974,
    "url": "https://reddit.com/r/wallstreetbets/",
    "timestamp": "2026-02-14T22:27:10.492106+00:00",
    "selftext": "Demo analysis for NVDA. This is fallback data - click to visit r/wallstreetbets.",
    "upvote_ratio": 0.7667082917873485,
    "over_18": false,
    "stickied": false,
    "comments": 271
  },
  {
    "id": "kukcizp",
    "title": "Why META is the play of the decade",
    "author": "user_3884",
    "subreddit": "investing",
    "score": 1393,
    "num_comments": 220,
    "created_utc": 1771082336.4915974,
    "url": "https://reddit.com/r/investing/",
    "timestamp": "2026-02-14T22:27:10.491870+00:00",
    "selftext": "Demo analysis for META. This is fallback data - click to visit r/investing.",
    "upvote_ratio": 0.9334476793590489,
    "over_18": false,
    "stickied": false,
    "comments": 95
  },
  {
    "id": "y32kkhb",
    "title": "AMC short squeeze potential?",
    "author": "user_9424",
    "subreddit": "investing",
    "score": 1301,
    "num_comments": 234,
    "created_utc": 1771100133.4915974,
    "url": "https://reddit.com/r/investing/",
    "timestamp": "2026-02-14T22:27:10.492008+00:00",
    "selftext": "Demo analysis for AMC. This is fallback data - click to visit r/investing.",
    "upvote_ratio": 0.8072560725190729,
    "over_18": false,
    "stickied": false,
    "comments": 59
  },
  {
    "id": "538vhqp",
    "title": "Why TSLA is the play of the decade",
    "author": "user_1538",
    "subreddit": "investing",
    "score": 1260,
    "num_comments": 243,
    "created_utc": 1771064895.4915974,
    "url": "https://reddit.com/r/investing/",
    "timestamp": "2026-02-14T22:27:10.491851+00:00",
    "selftext": "Demo analysis for TSLA. This is fallback data - click to visit r/investing.",
    "upvote_ratio": 0.7299676129694934,
    "over_18": false,
    "stickied": false,
    "comments": 181
  },
  {
    "id": "msacz9a",
    "title": "\ud83d\ude80 TSLA to the moon! DD inside",
    "author": "user_7497",
    "subreddit": "stocks",
    "score": 1241,
    "num_comments": 173,
    "created_utc": 1771077284.4915974,
    "url": "https://reddit.com/r/stocks/",
    "timestamp": "2026-02-14T22:27:10.492030+00:00",
    "selftext": "Demo analysis for TSLA. This is fallback data - click to visit r/stocks.",
    "upvote_ratio": 0.7033491812821138,
    "over_18": false,
    "stickied": false,
    "comments": 30
  },
  {
    "id": "tbgo2gr",
    "title": "Why AMC is the play of the decade",
    "author": "user_3773",
    "subreddit": "stocks",
    "score": 1222,
    "num_comments": 22,
    "created_utc": 1771092081.4915974,
    "url": "https://reddit.com/r/stocks/",
    "timestamp": "2026-02-14T22:27:10.492143+00:00",
    "selftext": "Demo analysis for AMC. This is fallback data - click to visit r/stocks.",
    "upvote_ratio": 0.9119990626612288,
    "over_18": false,
    "stickied": false,
    "comments": 47
  },
  {
    "id": "9sqkcb5",
    "title": "Hold or sell TSLA? Need advice",
    "author": "user_3979",
    "subreddit": "investing",
    "score": 1219,
    "num_comments": 77,
    "created_utc": 1771089505.4915974,
    "url": "https://reddit.com/r/investing/",
    "timestamp": "2026-02-14T22:27:10.491889+00:00",
    "selftext": "Demo analysis for TSLA. This is fallback data - click to visit r/investing.",
    "upvote_ratio": 0.8688473337232835,
    "over_18": false,
    "stickied": false,
    "comments": 213
  },
  {
    "id": "ox90rhr",
    "title": "Hold or sell META? Need advice",
    "author": "user_6177",
    "subreddit": "wallstreetbets",
    "score": 1088,
    "num_comments": 215,
    "created_utc": 1771079163.4915974,
    "url": "https://reddit.com/r/wallstreetbets/",
    "timestamp": "2026-02-14T22:27:10.491771+00:00",
    "selftext": "Demo analysis for META. This is fallback data - click to visit r/wallstreetbets.",
    "upvote_ratio": 0.826200957943969,
    "over_18": false,
    "stickied": false,
    "comments": 214
  },
  {
    "id": "ss2hevc",
    "title": "Hold or sell SPY? Need advice",
    "author": "user_9287",
    "subreddit": "stocks",
    "score": 1088,
    "num_comments": 239,
    "created_utc": 1771068238.4915974,
    "url": "https://reddit.com/r/stocks/",
    "timestamp": "2026-02-14T22:27:10.491810+00:00",
    "selftext": "Demo analysis for SPY. This is fallback data - click to visit r/stocks.",
    "upvote_ratio": 0.8379076942788095,
    "over_18": false,
    "stickied": false,
    "comments": 120
  },
  {
    "id": "lfpzizy",
    "title": "AAPL earnings beat expectations - bullish outlook",
    "author": "user_1023",
    "subreddit": "stocks",
    "score": 952,
    "num_comments": 91,
    "created_utc": 1771104424.4915974,
    "url": "https://reddit.com/r/stocks/",
    "timestamp": "2026-02-14T22:27:10.491907+00:00",
    "selftext": "Demo analysis for AAPL. This is fallback data - click to visit r/stocks.",
    "upvote_ratio": 0.8543128430257892,
    "over_18": false,
    "stickied": false,
    "comments": 21
  },
  {
    "id": "hu32y7p",
    "title": "NVDA news catalyst could spark rally",
    "author": "user_9223",
    "subreddit": "stocks",
    "score": 806,
    "num_comments": 191,
    "created_utc": 1771088445.4915974,
    "url": "https://reddit.com/r/stocks/",
    "timestamp": "2026-02-14T22:27:10.491791+00:00",
    "selftext": "Demo analysis for NVDA. This is fallback data - click to visit r/stocks.",
    "upvote_ratio": 0.7725296457880785,
    "over_18": false,
    "stickied": false,
    "comments": 237
  },
  {
    "id": "oyiq7ru",
    "title": "Why SPY is the play of the decade",
    "author": "user_3376",
    "subreddit": "stocks",
    "score": 647,
    "num_comments": 82,
    "created_utc": 1771068587.4915974,
    "url": "https://reddit.com/r/stocks/",
    "timestamp": "2026-02-14T22:27:10.491830+00:00",
    "selftext": "Demo analysis for SPY. This is fallback data - click to visit r/stocks.",
    "upvote_ratio": 0.7826830295656823,
    "over_18": false,
    "stickied": false,
    "comments": 90
  },
  {
    "id": "ejzzc4a",
    "title": "Technical analysis: TSLA breakout incoming",
    "author": "user_1237",
    "subreddit": "stocks",
    "score": 632,
    "num_comments": 190,
    "created_utc": 1771086738.4915974,
    "url": "https://reddit.com/r/stocks/",
    "timestamp": "2026-02-14T22:27:10.492086+00:00",
    "selftext": "Demo analysis for TSLA. This is fallback data - click to visit r/stocks.",
    "upvote_ratio": 0.8511517000906875,
    "over_18": false,
    "stickied": false,
    "comments": 22
  },
  {
    "id": "q4xensy",
    "title": "Hold or sell META? Need advice",
    "author": "user_3276",
    "subreddit": "stocks",
    "score": 400,
    "num_comments": 263,
    "created_utc": 1771070086.4915974,
    "url": "https://reddit.com/r/stocks/",
    "timestamp": "2026-02-14T22:27:10.491968+00:00",
    "selftext": "Demo analysis for META. This is fallback data - click to visit r/stocks.",
    "upvote_ratio": 0.8308636098799682,
    "over_18": false,
    "stickied": false,
    "comments": 251
  },
  {
    "id": "9icif7i",
    "title": "Technical analysis: SPY breakout incoming",
    "author": "user_1696",
    "subreddit": "stocks",
    "score": 376,
    "num_comments": 151,
    "created_utc": 1771088905.4915974,
    "url": "https://reddit.com/r/stocks/",
    "timestamp": "2026-02-14T22:27:10.491701+00:00",
    "selftext": "Demo analysis for SPY. This is fallback data - click to visit r/stocks.",
    "upvote_ratio": 0.8114795082509119,
    "over_18": false,
    "stickied": false,
    "comments": 239
  },
  {
    "id": "41u5uzu",
    "title": "MSFT news catalyst could spark rally",
    "author": "user_5855",
    "subreddit": "stocks",
    "score": 348,
    "num_comments": 45,
    "created_utc": 1771087153.4915974,
    "url": "https://reddit.com/r/stocks/",
    "timestamp": "2026-02-14T22:27:10.492161+00:00",
    "selftext": "Demo analysis for MSFT. This is fallback data - click to visit r/stocks.",
    "upvote_ratio": 0.8637681765855972,
    "over_18": false,
    "stickied": false,
    "comments": 299
  },
  {
    "id": "u466ezv",
    "title": "Bought 1000 shares of SPY - YOLO",
    "author": "user_2613",
    "subreddit": "investing",
    "score": 289,
    "num_comments": 211,
    "created_utc": 1771098705.4915974,
    "url": "https://reddit.com/r/investing/",
    "timestamp": "2026-02-14T22:27:10.491990+00:00",
    "selftext": "Demo analysis for SPY. This is fallback data - click to visit r/investing.",
    "upvote_ratio": 0.7085796321012818,
    "over_18": false,
    "stickied": false,
    "comments": 232
  }
]